dbt/__init__.py
dbt/adapters/__init__.py
dbt/adapters/rockset/__init__.py
dbt/adapters/rockset/__version__.py
dbt/adapters/rockset/column.py
dbt/adapters/rockset/connections.py
dbt/adapters/rockset/impl.py
dbt/adapters/rockset/relation.py
dbt/include/__init__.py
dbt/include/rockset/__init__.py
dbt/include/rockset/dbt_project.yml
dbt/include/rockset/profile_template.yml
dbt/include/rockset/macros/catalog.sql
dbt/include/rockset/macros/current_ts.sql
dbt/include/rockset/macros/macros.sql
dbt/include/rockset/macros/materializations/incremental.sql
dbt/include/rockset/macros/materializations/query_lambda.sql
dbt/include/rockset/macros/materializations/seed.sql
dbt/include/rockset/macros/materializations/table.sql
dbt/include/rockset/macros/materializations/view.sql
dbt_rockset-1.7.4.dist-info/METADATA
dbt_rockset-1.7.4.dist-info/WHEEL
dbt_rockset-1.7.4.dist-info/top_level.txt
dbt_rockset-1.7.4.dist-info/RECORD
